foaas.py
foaas-0.2.0.dist-info/RECORD
foaas-0.2.0.dist-info/top_level.txt
foaas-0.2.0.dist-info/METADATA
foaas-0.2.0.dist-info/DESCRIPTION.rst
foaas-0.2.0.dist-info/WHEEL
foaas-0.2.0.dist-info/metadata.json
