Metadata-Version: 2.0
Name: foaas
Version: 0.2.0
Summary: Fuck Off As A Service
Home-page: https://github.com/dmpayton/foaas-python
Author: Derek Payton
Author-email: derek.payton@gmail.com
License: MIT
Platform: UNKNOWN
Classifier: Development Status :: 4 - Beta
Classifier: Intended Audience :: Developers
Classifier: License :: OSI Approved :: MIT License
Classifier: Natural Language :: English
Classifier: Programming Language :: Python
Classifier: Topic :: Software Development :: Testing
Requires-Dist: requests
